cjmls.py
cjmls-0.0.2.dist-info/DESCRIPTION.rst
cjmls-0.0.2.dist-info/METADATA
cjmls-0.0.2.dist-info/RECORD
cjmls-0.0.2.dist-info/WHEEL
cjmls-0.0.2.dist-info/metadata.json
cjmls-0.0.2.dist-info/top_level.txt
