Metadata-Version: 2.0
Name: cjmls
Version: 0.0.2
Summary: Python wrapper for cjmls.
Home-page: https://github.com/AlJohri/cjmls
Author: Al Johri
Author-email: al.johri@gmail.com
License: MIT
Platform: UNKNOWN
Classifier: Programming Language :: Python :: 3 :: Only
Classifier: Programming Language :: Python :: 3.6
Classifier: License :: OSI Approved :: MIT License
Requires-Dist: requests
